RFPlasmid/Bacillus.rfo
RFPlasmid/Borrelia.rfo
RFPlasmid/Burkholderia.rfo
RFPlasmid/Campylobacter.rfo
RFPlasmid/Clostridium.rfo
RFPlasmid/Corynebacterium.rfo
RFPlasmid/Cyanothece.rfo
RFPlasmid/Enterobacteriaceae.rfo
RFPlasmid/Enterococcus.rfo
RFPlasmid/Generic.rfo
RFPlasmid/Lactobacillus.rfo
RFPlasmid/Lactococcus.rfo
RFPlasmid/Listeria.rfo
RFPlasmid/Pseudomonas.rfo
RFPlasmid/Rhizobium.rfo
RFPlasmid/Staphylococcus.rfo
RFPlasmid/Streptomyces.rfo
RFPlasmid/Vibrio.rfo
RFPlasmid/__init__.py
RFPlasmid/classification.R
RFPlasmid/getdb.sh
RFPlasmid/kmer.txt
RFPlasmid/rfplasmid.py
RFPlasmid/specieslist.txt
RFPlasmid/training.R
rfplasmid-1.0.data/scripts/rfplasmid
rfplasmid-1.0.dist-info/LICENSE
rfplasmid-1.0.dist-info/METADATA
rfplasmid-1.0.dist-info/WHEEL
rfplasmid-1.0.dist-info/top_level.txt
rfplasmid-1.0.dist-info/RECORD
