Metadata-Version: 2.1
Name: rfplasmid
Version: 1.0
Summary: RFPlasmid Predicting plasmid contigs
Home-page: https://github.com/aldertzomer/RFPlasmid
Author: Aldert Zomer
Author-email: A.L.Zomer@uu.nl
License: UNKNOWN
Download-URL: https://github.com/aldertzomer/RFPlasmid/archive/0.0.18.tar.gz
Platform: UNKNOWN
Classifier: Programming Language :: Python :: 3
Classifier: License :: OSI Approved :: GNU General Public License v3 (GPLv3)
Classifier: Operating System :: POSIX :: Linux
Requires-Dist: biopython
Requires-Dist: pandas
Requires-Dist: numpy
Requires-Dist: matplotlib
Requires-Dist: pysam
Requires-Dist: checkm-genome
